tests/__init__.py
tests/test_vaporipsum.py
tests/test_vaporize.py
vaporwavely/__init__.py
vaporwavely/utils.py
vaporwavely/vaporwavely.py
vaporwavely-1.0.1.dist-info/DESCRIPTION.rst
vaporwavely-1.0.1.dist-info/METADATA
vaporwavely-1.0.1.dist-info/RECORD
vaporwavely-1.0.1.dist-info/WHEEL
vaporwavely-1.0.1.dist-info/metadata.json
vaporwavely-1.0.1.dist-info/top_level.txt
