Metadata-Version: 2.0
Name: vaporwavely
Version: 1.0.1
Summary: An extremely fast library to vaporize your text and many more!
Home-page: https://github.com/Owanesh/vaporwavely
Author: Owanesh
Author-email: UNKNOWN
License: MIT
Platform: UNKNOWN
Classifier: Programming Language :: Python
Classifier: Programming Language :: Python :: 3
